{"cameraMode":{"drawMode":0,"name":"Shaded","section":"Shading Mode"},"sceneLighting":true,"audioPlay":false,"sceneViewState":{"m_AlwaysRefresh":false,"showFog":true,"showSkybox":false,"showFlares":true,"showImageEffects":true,"showParticleSystems":true,"showVisualEffectGraphs":true,"m_FxEnabled":true},"in2DMode":false,"pivot":{"x":-8.388071060180664,"y":-5.058323860168457,"z":-4.412283897399902},"rotation":{"x":0.211466982960701,"y":-0.6563907861709595,"z":0.19937728345394135,"w":0.6961637735366821},"size":9.823441505432129,"orthographic":false}